{"name":"build-javascript","namedChunkGroups":{"app":{"name":"app","assets":[{"name":"webpack-runtime-6b32b3776d69c333e210.js","size":3591},{"name":"framework-6cf00bcf702f68aabf35.js","size":140324},{"name":"styles.6e706bf8ed729b03c0ba.css","size":9764},{"name":"app-f350e9a1aa268978547f.js","size":61071}],"filteredAssets":0,"assetsSize":214750,"filteredAuxiliaryAssets":3,"auxiliaryAssetsSize":589120},"component---src-pages-404-tsx":{"name":"component---src-pages-404-tsx","assets":[{"name":"component---src-pages-404-tsx-eb5505c9e788d0821004.js","size":761}],"filteredAssets":0,"assetsSize":761,"filteredAuxiliaryAssets":1,"auxiliaryAssetsSize":1898},"component---src-pages-index-tsx":{"name":"component---src-pages-index-tsx","assets":[{"name":"component---src-pages-index-tsx-661e631d580200cb7751.js","size":11088}],"filteredAssets":0,"assetsSize":11088,"filteredAuxiliaryAssets":1,"auxiliaryAssetsSize":20208}},"assetsByChunkName":{"app":["webpack-runtime-6b32b3776d69c333e210.js","framework-6cf00bcf702f68aabf35.js","styles.6e706bf8ed729b03c0ba.css","app-f350e9a1aa268978547f.js"],"component---src-pages-404-tsx":["component---src-pages-404-tsx-eb5505c9e788d0821004.js"],"component---src-pages-index-tsx":["component---src-pages-index-tsx-661e631d580200cb7751.js"]},"childAssetsByChunkName":{}}